gosei/__init__.py
gosei/main.py
gosei-0.1.0.dist-info/entry_points.txt
gosei-0.1.0.dist-info/WHEEL
gosei-0.1.0.dist-info/METADATA
gosei-0.1.0.dist-info/RECORD
